langware/__init__.py
langware/chat.py
langware/function.py
langware/logger.py
langware/model.py
langware/prompt.py
langware/utilities/__init__.py
langware/utilities/common.py
Langware-0.1.dist-info/LICENSE-APACHE-2.0
Langware-0.1.dist-info/LICENSE-MIT
Langware-0.1.dist-info/METADATA
Langware-0.1.dist-info/WHEEL
Langware-0.1.dist-info/top_level.txt
Langware-0.1.dist-info/RECORD
