Metadata-Version: 2.1
Name: Langware
Version: 0.1
Summary: Lightweight, powerful and hassle-free Langchain alternative.
Home-page: https://github.com/langware-ai/langware
Author: Ivan Stepanov
Author-email: ivanstepanovftw@gmail.com
Keywords: langchain openai llama llamacpp chat gpt
Classifier: Development Status :: 3 - Alpha
Classifier: Intended Audience :: Developers
Classifier: Topic :: Software Development :: Libraries
Classifier: License :: OSI Approved :: MIT License
Classifier: License :: OSI Approved :: Apache Software License
Classifier: Programming Language :: Python :: 3.8
Classifier: Programming Language :: Python :: 3.9
Classifier: Programming Language :: Python :: 3.10
Classifier: Programming Language :: Python :: 3.11
Classifier: Operating System :: OS Independent
Requires-Python: >=3.8, <4
License-File: LICENSE-APACHE-2.0
License-File: LICENSE-MIT
Requires-Dist: pydantic <3,>=2
Requires-Dist: aiohttp <4,>=3
Requires-Dist: colorama ~=0.4.6
